procaaso_client/asynchronous/__init__.py
procaaso_client/asynchronous/application.py
procaaso_client/asynchronous/client.py
procaaso_client/core/__init__.py
procaaso_client/core/base.py
procaaso_client/core/client_models.py
procaaso_client/core/http_clients.py
procaaso_client/synchronous/__init__.py
procaaso_client/synchronous/application.py
procaaso_client/synchronous/client.py
procaaso_client-0.1.19.dist-info/LICENSE
procaaso_client-0.1.19.dist-info/METADATA
procaaso_client-0.1.19.dist-info/WHEEL
procaaso_client-0.1.19.dist-info/RECORD
