Metadata-Version: 2.1
Name: procaaso_client
Version: 0.1.19
Summary: 
Author: Procaaso
Author-email: bsmith_devops@outlook.com
Requires-Python: >=3.10,<4.0
Classifier: Programming Language :: Python :: 3
Classifier: Programming Language :: Python :: 3.10
Classifier: Programming Language :: Python :: 3.11
Classifier: Programming Language :: Python :: 3.12
Requires-Dist: exceptiongroup (>=1.2.0,<2.0.0)
Requires-Dist: httpcore[asyncio] (>=1.0.3,<2.0.0)
Requires-Dist: httpx[http2] (>=0.28.1,<0.29.0)
Requires-Dist: procaaso-log (>=0.3.2,<0.4.0)
